docs/conf.py
picodi/__init__.py
picodi/_inject.py
picodi/_internal.py
picodi/_registry.py
picodi/_scopes.py
picodi/_types.py
picodi/helpers.py
picodi/py.typed
picodi/support.py
picodi/integrations/__init__.py
picodi/integrations/_pytest.py
picodi/integrations/_pytest_asyncio.py
picodi/integrations/fastapi.py
picodi/integrations/starlette.py
picodi-0.36.6.dist-info/licenses/LICENSE
picodi-0.36.6.dist-info/METADATA
picodi-0.36.6.dist-info/WHEEL
picodi-0.36.6.dist-info/top_level.txt
picodi-0.36.6.dist-info/zip-safe
picodi-0.36.6.dist-info/RECORD
